Assignment2/parity.vhd
-- 8-bit parity generator
--   t = 0 for even parity
--   t = 1 for  odd parity
library ieee;
use ieee.std_logic_1164.all;
use ieee.numeric_std.all;

entity parity is
port (
    a : in std_logic_vector(7 downto 0);
    t : in std_logic;
    p : out std_logic
);
end parity;

architecture rtl of parity is
begin

    process(a, t) is
        variable x: std_logic := '0';
    begin
        -- 0 out x in the beginning of process
        x := '0';
        for i in a'range loop
            x := x xor a(i);
        end loop;

        p <= x xor t;
    end process;

end rtl;

Assignment2/tb_parity.vhd
-- parity calculation testbench
library ieee;
use ieee.std_logic_1164.all;
use ieee.numeric_std.all;

entity tb_parity is
end tb_parity;

architecture bhv of tb_parity is
    signal a : std_logic_vector(7 downto 0) := (others => '0');
    signal t, p : std_logic;
begin

    uut : entity work.parity(rtl)
      port map( a => a, t => t, p => p);

    process
    begin
        -- testing for even parity
        t <= '0';
        a <= (others => '0');
        wait for 10 ns;
        a <= "01000000";
        wait for 10 ns;
        a <= "00000001";
        wait for 10 ns;
        a <= "01000100";
        wait for 10 ns;
        a <= "01010010";
        wait for 10 ns;
        a <= "01010011";
        wait for 10 ns;
        a <= "11111111";
        wait for 30 ns;
        -- testing for odd parity
        t <= '1';
        a <= (others => '0');
        wait for 10 ns;
        a <= "01000000";
        wait for 10 ns;
        a <= "00000001";
        wait for 10 ns;
        a <= "01000100";
        wait for 10 ns;
        a <= "01010010";
        wait for 10 ns;
        a <= "01010011";
        wait for 10 ns;
        a <= "11111111";
        wait for 10 ns;
        wait;
    end process;

end bhv;

Assignment2/parity.vcd
$date
  Tue Feb 08 17:22:45 2022
$end
$version
  GHDL v0
$end
$timescale
  1 fs
$end
$scope module standard $end
$upscope $end
$scope module std_logic_1164 $end
$upscope $end
$scope module numeric_std $end
$upscope $end
$scope module tb_parity $end
$var reg 8 ! a[7:0] $end
$var reg 1 " t $end
$var reg 1 # p $end
$scope module uut $end
$var reg 8 $ a[7:0] $end
$var reg 1 % t $end
$var reg 1 & p $end
$upscope $end
$upscope $end
$enddefinitions $end
#0
b00000000 !
0"
0#
b00000000 $
0%
0&
#10000000
b01000000 !
1#
b01000000 $
1&
#20000000
b00000001 !
b00000001 $
#30000000
b01000100 !
0#
b01000100 $
0&
#40000000
b01010010 !
1#
b01010010 $
1&
#50000000
b01010011 !
0#
b01010011 $
0&
#60000000
b11111111 !
b11111111 $
#90000000
b00000000 !
1"
1#
b00000000 $
1%
1&
#100000000
b01000000 !
0#
b01000000 $
0&
#110000000
b00000001 !
b00000001 $
#120000000
b01000100 !
1#
b01000100 $
1&
#130000000
b01010010 !
0#
b01010010 $
0&
#140000000
b01010011 !
1#
b01010011 $
1&
#150000000
b11111111 !
b11111111 $
